xquant/__init__.py
xquant/conf.py
xquant/engine/__init__.py
xquant/engine/backtest.py
xquant/engine/commission.py
xquant/engine/data.py
xquant/engine/event.py
xquant/engine/execution.py
xquant/engine/portfolio.py
xquant/engine/slippage.py
xquant/engine/strategy.py
xquant/finance/__init__.py
xquant/finance/benefit.py
xquant/finance/perform.py
xquant/utils/__init__.py
xquant/utils/alternative.py
xquant/utils/bayesopt.py
xquant/utils/logger.py
xquant/utils/parallel.py
xquant/utils/profiler.py
xquant/utils/pytalib.py
xquant/utils/symbol.py
xquant/utils/timeutil.py
xquant/visual/__init__.py
xquant/visual/chart.py
xquant-0.5.2.dist-info/DESCRIPTION.rst
xquant-0.5.2.dist-info/METADATA
xquant-0.5.2.dist-info/RECORD
xquant-0.5.2.dist-info/WHEEL
xquant-0.5.2.dist-info/metadata.json
xquant-0.5.2.dist-info/top_level.txt
